eshop_prices/__init__.py
eshop_prices/eshop.py
eshop_prices-0.1.0.dist-info/METADATA
eshop_prices-0.1.0.dist-info/WHEEL
eshop_prices-0.1.0.dist-info/RECORD
