Metadata-Version: 2.1
Name: eshop-prices
Version: 0.1.0
Summary: 
Author: Hudson Brendon
Author-email: contato.hudsonbrendon@gmail.com
Requires-Python: >=3.10,<4.0
Classifier: Programming Language :: Python :: 3
Classifier: Programming Language :: Python :: 3.10
Classifier: Programming Language :: Python :: 3.11
Requires-Dist: beautifulsoup4 (>=4.12.0,<5.0.0)
Requires-Dist: cchardet (>=2.1.7,<3.0.0)
Requires-Dist: lxml (>=4.9.2,<5.0.0)
Requires-Dist: pytest (>=7.2.2,<8.0.0)
Requires-Dist: requests (>=2.28.2,<3.0.0)
